github_cards/__init__.py
github_cards/cli.py
github_cards/decorators.py
github_cards/exceptions.py
github_cards/filters.py
github_cards/otp_cache.py
github_cards/rendering.py
github_cards/templates/index.html
github_cards-0.1.22.dist-info/AUTHORS.rst
github_cards-0.1.22.dist-info/LICENSE
github_cards-0.1.22.dist-info/METADATA
github_cards-0.1.22.dist-info/WHEEL
github_cards-0.1.22.dist-info/entry_points.txt
github_cards-0.1.22.dist-info/top_level.txt
github_cards-0.1.22.dist-info/RECORD
