Metadata-Version: 2.1
Name: github-cards
Version: 0.1.22
Summary: Convert your GitHub issues into printable cards for your physical Scrum/Kanban board.
Home-page: https://github.com/larsrinn/github_cards
Author: Lars Rinn
Author-email: lm.rinn@outlook.com
License: MIT license
Keywords: github_cards
Platform: UNKNOWN
Classifier: Development Status :: 2 - Pre-Alpha
Classifier: Intended Audience :: Developers
Classifier: License :: OSI Approved :: MIT License
Classifier: Natural Language :: English
Classifier: Programming Language :: Python :: 3.6
Classifier: Programming Language :: Python :: 3.7
Requires-Dist: Click (>=6.0)
Requires-Dist: Jinja2
Requires-Dist: github3.py
Requires-Dist: colorama
